nsepython2/__init__.py
nsepython2/py.typed
nsepython2/rahu.py
nsepython2-0.1.0.dist-info/METADATA
nsepython2-0.1.0.dist-info/WHEEL
nsepython2-0.1.0.dist-info/RECORD
