Metadata-Version: 2.4
Name: nsepython2
Version: 0.1.0
Summary: Fork of nsepython
Author-email: Anurag Roy <anuragroy11@gmail.com>
Requires-Python: >=3.13
Requires-Dist: pandas>=2.2.3
Requires-Dist: requests>=2.32.3
Requires-Dist: scipy>=1.15.3
